yabi/__init__.py
yabi/__main__.py
yabi/config.py
yabi/console.py
yabi/convert.py
yabi/parser.py
yabi/runner.py
yabi_bython-0.8.3.dist-info/METADATA
yabi_bython-0.8.3.dist-info/WHEEL
yabi_bython-0.8.3.dist-info/entry_points.txt
yabi_bython-0.8.3.dist-info/licenses/LICENSE.md
yabi_bython-0.8.3.dist-info/RECORD
