Metadata-Version: 2.4
Name: yabi-bython
Version: 0.8.3
Summary: Yet Another Bython (braced Python) Implementation
Project-URL: Repository, https://github.com/solaluset/yabi
Author: Sóla Lusøt
License-Expression: MIT
License-File: LICENSE.md
Requires-Dist: pwcp<0.13,>=0.12
Provides-Extra: tests
Requires-Dist: pytest; extra == 'tests'
